pgdont/__init__.py
pgdont/ruler.py
pgdont/rules/__init__.py
pgdont/rules/database_encoding_rule.py
pgdont/rules/date_time_rules.py
pgdont/rules/i_rule.py
pgdont/rules/inheritance_rule.py
pgdont/rules/rules_rule.py
pgdont/rules/upper_case_column_rule.py
pgdont/rules/upper_case_table_rule.py
tests/__init__.py
tests/database_test_case.py
tests/test_ruler.py
tests/test_rules.py
pgDont-0.0.2.dist-info/LICENCE
pgDont-0.0.2.dist-info/METADATA
pgDont-0.0.2.dist-info/WHEEL
pgDont-0.0.2.dist-info/entry_points.txt
pgDont-0.0.2.dist-info/top_level.txt
pgDont-0.0.2.dist-info/RECORD
