Metadata-Version: 2.1
Name: pgDont
Version: 0.0.2
Summary: Auditing tool for postgres best practices
Home-page: https://gitlab.com/amden/pgdont
Author: amden
Author-email: me+pypi@amden.xyz
License: UNKNOWN
Platform: UNKNOWN
Classifier: Programming Language :: Python :: 3
Classifier: License :: OSI Approved :: MIT License
Classifier: Operating System :: OS Independent
Classifier: Topic :: Software Development
Classifier: Topic :: Software Development :: Quality Assurance
Requires-Python: >=3.6
Requires-Dist: click (>=7.1.2)
Requires-Dist: psycopg2-binary (>=2.8.6)
Provides-Extra: tests
Requires-Dist: pytest ; extra == 'tests'
Requires-Dist: pytest-pep8 ; extra == 'tests'
Requires-Dist: pytest-cov ; extra == 'tests'
Requires-Dist: pytest-flake8 ; extra == 'tests'
Requires-Dist: pytest-isort ; extra == 'tests'
Requires-Dist: testing.postgresql ; extra == 'tests'
